Metadata-Version: 2.1
Name: snake-game
Version: 0.1
Summary: Snake Game.
Home-page: UNKNOWN
Author: Ravi Kumar Nimmi
Author-email: nimmi.ravikumar@gmail.com
License: UNKNOWN
Keywords: snake game
Platform: UNKNOWN
